LICENSE
README.rst
setup.cfg
setup.py
pytechfin/__init__.py
pytechfin/auth.py
pytechfin/carol_sync_monitoring.py
pytechfin/carol_techfin.py
pytechfin/context.py
pytechfin/enums.py
pytechfin/exceptions.py
pytechfin/http.py
pytechfin/misc.py
pytechfin/provisioning.py
pytechfin/pubsub.py
pytechfin/techfin.py
pytechfin.egg-info/PKG-INFO
pytechfin.egg-info/SOURCES.txt
pytechfin.egg-info/dependency_links.txt
pytechfin.egg-info/requires.txt
pytechfin.egg-info/top_level.txt