Metadata-Version: 2.1
Name: pytechfin
Version: 1.0.1
Summary: Techfin Python API and Tools
Home-page: https://github.com/jnefoussi/pytechfin
Author: Jonathan J Nefoussi
Author-email: jnefoussi@gmail.com
Maintainer: Jonathan J Nefoussi
License: MIT
Keywords: TOTVS Techfin,Carol.ai,TOTVS
Platform: UNKNOWN
Classifier: Development Status :: 5 - Production/Stable
Classifier: Intended Audience :: Developers
Classifier: Topic :: Software Development :: Build Tools
Classifier: License :: OSI Approved :: MIT License
Classifier: Programming Language :: Python :: 3.6
Classifier: Operating System :: OS Independent
Provides-Extra: complete
License-File: LICENSE
